{
  "openapi": "3.0.0",
  "info": {
    "title": "Project Name API",
    "version": "1.0.0",
    "description": ""
  },
  "servers": [
    {
      "url": "http://localhost:3000"
    }
  ],
  "paths": {
    "/userRoutes/signup": {
      "post": {
        "description": "",
        "responses": {
          "201": {
            "description": "Created"
          },
          "400": {
            "description": "Bad Request"
          },
          "409": {
            "description": "Conflict"
          },
          "500": {
            "description": "Internal Server Error"
          }
        },
        "requestBody": {
          "content": {
            "application/json": {
              "schema": {
                "type": "object",
                "properties": {
                  "email": {
                    "example": "any"
                  },
                  "password": {
                    "example": "any"
                  },
                  "fullName": {
                    "example": "any"
                  }
                }
              }
            }
          }
        },
        "tags": [
          "userRoutes"
        ]
      }
    },
    "/userRoutes/login": {
      "post": {
        "description": "",
        "responses": {
          "200": {
            "description": "OK"
          },
          "400": {
            "description": "Bad Request"
          },
          "401": {
            "description": "Unauthorized"
          },
          "404": {
            "description": "Not Found"
          },
          "500": {
            "description": "Internal Server Error"
          }
        },
        "requestBody": {
          "content": {
            "application/json": {
              "schema": {
                "type": "object",
                "properties": {
                  "email": {
                    "example": "any"
                  },
                  "password": {
                    "example": "any"
                  }
                }
              }
            }
          }
        },
        "tags": [
          "userRoutes"
        ]
      }
    },
    "/userRoutes/check": {
      "get": {
        "description": "",
        "responses": {
          "200": {
            "description": "OK"
          },
          "401": {
            "description": "Unauthorized"
          },
          "500": {
            "description": "Internal Server Error"
          }
        },
        "tags": [
          "userRoutes"
        ]
      }
    },
    "/userRoutes/update": {
      "patch": {
        "description": "",
        "responses": {
          "200": {
            "description": "OK"
          },
          "400": {
            "description": "Bad Request"
          },
          "401": {
            "description": "Unauthorized"
          },
          "500": {
            "description": "Internal Server Error"
          }
        },
        "requestBody": {
          "content": {
            "application/json": {
              "schema": {
                "type": "object",
                "properties": {
                  "fullName": {
                    "example": "any"
                  },
                  "currency": {
                    "example": "any"
                  }
                }
              }
            }
          }
        },
        "tags": [
          "userRoutes"
        ]
      }
    },
    "/moneyRoutes/addTransaction": {
      "post": {
        "description": "",
        "responses": {
          "201": {
            "description": "Created"
          },
          "400": {
            "description": "Bad Request"
          },
          "401": {
            "description": "Unauthorized"
          },
          "500": {
            "description": "Internal Server Error"
          }
        },
        "requestBody": {
          "content": {
            "application/json": {
              "schema": {
                "type": "object",
                "properties": {
                  "type": {
                    "example": "any"
                  },
                  "paymentType": {
                    "example": "any"
                  },
                  "description": {
                    "example": "any"
                  },
                  "amount": {
                    "example": "any"
                  },
                  "date": {
                    "example": "any"
                  },
                  "category": {
                    "example": "any"
                  }
                }
              }
            }
          }
        },
        "tags": [
          "moneyRoutes"
        ]
      }
    },
    "/moneyRoutes/getTransactions": {
      "get": {
        "description": "",
        "parameters": [
          {
            "name": "type",
            "in": "query",
            "schema": {
              "type": "string"
            }
          },
          {
            "name": "search",
            "in": "query",
            "schema": {
              "type": "string"
            }
          }
        ],
        "responses": {
          "200": {
            "description": "OK"
          },
          "401": {
            "description": "Unauthorized"
          },
          "500": {
            "description": "Internal Server Error"
          }
        },
        "tags": [
          "moneyRoutes"
        ]
      }
    },
    "/moneyRoutes/getTransactionSummary": {
      "get": {
        "description": "",
        "responses": {
          "200": {
            "description": "OK"
          },
          "401": {
            "description": "Unauthorized"
          },
          "500": {
            "description": "Internal Server Error"
          }
        },
        "tags": [
          "moneyRoutes"
        ]
      }
    },
    "/moneyRoutes/deleteTransaction/{id}": {
      "delete": {
        "description": "",
        "parameters": [
          {
            "name": "id",
            "in": "path",
            "required": true,
            "schema": {
              "type": "string"
            }
          }
        ],
        "responses": {
          "200": {
            "description": "OK"
          },
          "401": {
            "description": "Unauthorized"
          },
          "404": {
            "description": "Not Found"
          },
          "500": {
            "description": "Internal Server Error"
          }
        },
        "tags": [
          "moneyRoutes"
        ]
      }
    }
  }
}